ChaterJee/ChaterJee.py
ChaterJee/__init__.py
chaterjee-0.9.4.dist-info/METADATA
chaterjee-0.9.4.dist-info/WHEEL
chaterjee-0.9.4.dist-info/entry_points.txt
chaterjee-0.9.4.dist-info/top_level.txt
chaterjee-0.9.4.dist-info/RECORD
