Metadata-Version: 2.4
Name: ChaterJee
Version: 0.9.4
Summary: Communicate your project updates via Telegram Bot!
Author: Pallab Dutta
Author-email: pallab9997@gmail.com
Requires-Python: >=3.8
Requires-Dist: python-telegram-bot==20.7
Requires-Dist: python-telegram-bot[job-queue]
Dynamic: author
Dynamic: author-email
Dynamic: description
Dynamic: description-content-type
Dynamic: requires-dist
Dynamic: requires-python
Dynamic: summary
